tests/__init__.py
tests/test_access.py
tests/test_apache.py
tests/test_api.py
tests/test_caldav.py
tests/test_caldav_filters.py
tests/test_carddav.py
tests/test_carddav_filters.py
tests/test_collation.py
tests/test_config.py
tests/test_davcommon.py
tests/test_expand_property.py
tests/test_icalendar.py
tests/test_insufficient_index_handling.py
tests/test_main.py
tests/test_performance.py
tests/test_post.py
tests/test_quota.py
tests/test_rrule_index_usage.py
tests/test_scheduling.py
tests/test_store.py
tests/test_store_regression.py
tests/test_sync.py
tests/test_timezones.py
tests/test_vcard.py
tests/test_web.py
tests/test_webdav.py
tests/test_wsgi.py
tests/test_wsgi_helpers.py
xandikos/__init__.py
xandikos/__main__.py
xandikos/access.py
xandikos/apache.py
xandikos/caldav.py
xandikos/carddav.py
xandikos/collation.py
xandikos/davcommon.py
xandikos/icalendar.py
xandikos/infit.py
xandikos/py.typed
xandikos/quota.py
xandikos/scheduling.py
xandikos/server_info.py
xandikos/sync.py
xandikos/timezones.py
xandikos/vcard.py
xandikos/web.py
xandikos/webdav.py
xandikos/wsgi.py
xandikos/wsgi_helpers.py
xandikos/xmpp.py
xandikos/store/__init__.py
xandikos/store/config.py
xandikos/store/git.py
xandikos/store/index.py
xandikos/store/memory.py
xandikos/store/vdir.py
xandikos/templates/collection.html
xandikos/templates/principal.html
xandikos/templates/root.html
xandikos-0.3.3.dist-info/licenses/AUTHORS
xandikos-0.3.3.dist-info/licenses/COPYING
xandikos-0.3.3.dist-info/METADATA
xandikos-0.3.3.dist-info/WHEEL
xandikos-0.3.3.dist-info/entry_points.txt
xandikos-0.3.3.dist-info/top_level.txt
xandikos-0.3.3.dist-info/RECORD
