Metadata-Version: 2.4
Name: xandikos
Version: 0.3.3
Summary: Lightweight CalDAV/CardDAV server
Author-email: Jelmer Vernooij <jelmer@jelmer.uk>
License: GNU GPLv3 or later
Project-URL: Homepage, https://www.xandikos.org/
Classifier: Development Status :: 4 - Beta
Classifier: License :: OSI Approved :: GNU General Public License v3 or later (GPLv3+)
Classifier: Programming Language :: Python :: 3.10
Classifier: Programming Language :: Python :: 3.11
Classifier: Programming Language :: Python :: 3.12
Classifier: Programming Language :: Python :: 3.13
Classifier: Programming Language :: Python :: 3.14
Classifier: Programming Language :: Python :: Implementation :: CPython
Classifier: Programming Language :: Python :: Implementation :: PyPy
Classifier: Operating System :: POSIX
Requires-Python: >=3.10
License-File: COPYING
License-File: AUTHORS
Requires-Dist: aiohttp
Requires-Dist: icalendar<7.0,>=5.0.4
Requires-Dist: dulwich<2,>=0.25.0
Requires-Dist: defusedxml
Requires-Dist: jinja2
Requires-Dist: multidict
Requires-Dist: vobject
Provides-Extra: prometheus
Requires-Dist: aiohttp-openmetrics; extra == "prometheus"
Provides-Extra: systemd
Requires-Dist: systemd_python; extra == "systemd"
Provides-Extra: qrcode
Requires-Dist: qrcode[pil]; extra == "qrcode"
Provides-Extra: dev
Requires-Dist: ruff==0.14.10; extra == "dev"
Requires-Dist: pytest; extra == "dev"
Provides-Extra: typing
Requires-Dist: mypy==1.19.1; extra == "typing"
Requires-Dist: types-python-dateutil; extra == "typing"
Dynamic: license-file
